Metadata-Version: 2.1
Name: rocketdina
Version: 1.0.0
Summary: An awesome package that does something
Home-page: http://pypi.python.org/pypi/rocketdina/
Author: dinaftc
Author-email: d.fettache@esi-sba.dz
License: LICENSE.txt
